ami_data_parser/__init__.py
ami_data_parser/controller.py
ami_data_parser/entities/__init__.py
ami_data_parser/entities/call.py
ami_data_parser/entities/channel.py
ami_data_parser/entities/core.py
ami_data_parser/entities/member.py
ami_data_parser/entities/peer.py
ami_data_parser/entities/queue.py
ami_data_parser/entities/queue_member.py
ami_data_parser/factories/__init__.py
ami_data_parser/factories/call_factory.py
ami_data_parser/factories/channel_factory.py
ami_data_parser/factories/member_factory.py
ami_data_parser/factories/peer_factory.py
ami_data_parser/factories/queue_factory.py
ami_data_parser/factories/queue_member_factory.py
ami_data_parser/parser/__init__.py
ami_data_parser/parser/channel_parser.py
ami_data_parser/parser/core.py
ami_data_parser/parser/hint_parser.py
ami_data_parser/parser/queue_parser.py
ami_data_parser/parser/utils.py
ami_data_parser/repositories/__init__.py
ami_data_parser/repositories/call_repository.py
ami_data_parser/repositories/channel_repository.py
ami_data_parser/repositories/core.py
ami_data_parser/repositories/member_repository.py
ami_data_parser/repositories/peer_repository.py
ami_data_parser/repositories/queue_repository.py
ami_data_parser/tests/__init__.py
ami_data_parser/tests/test_call.py
ami_data_parser/tests/test_call_factory.py
ami_data_parser/tests/test_call_repository.py
ami_data_parser/tests/test_channel.py
ami_data_parser/tests/test_channel_parser.py
ami_data_parser/tests/test_channel_repository.py
ami_data_parser/tests/test_controller.py
ami_data_parser/tests/test_hint_parser.py
ami_data_parser/tests/test_member.py
ami_data_parser/tests/test_member_factory.py
ami_data_parser/tests/test_member_repository.py
ami_data_parser/tests/test_parsers_utils.py
ami_data_parser/tests/test_peer.py
ami_data_parser/tests/test_peer_factory.py
ami_data_parser/tests/test_peer_repository.py
ami_data_parser/tests/test_queue.py
ami_data_parser/tests/test_queue_factory.py
ami_data_parser/tests/test_queue_member_factory.py
ami_data_parser-0.2.13.dist-info/licenses/LICENSE
ami_data_parser-0.2.13.dist-info/METADATA
ami_data_parser-0.2.13.dist-info/WHEEL
ami_data_parser-0.2.13.dist-info/top_level.txt
ami_data_parser-0.2.13.dist-info/RECORD
