Metadata-Version: 2.4
Name: ami-data-parser
Version: 0.2.13
Summary: AMI parser data
Author: Tatianno Alves
Author-email: tferreiraalves@gmail.com
License: MIT License
Keywords: asterisk manager interface ami parser data
License-File: LICENSE
Dynamic: author
Dynamic: author-email
Dynamic: description
Dynamic: description-content-type
Dynamic: keywords
Dynamic: license
Dynamic: license-file
Dynamic: summary
